shosai/__init__.py
shosai/app.py
shosai/langhelpers.py
shosai/loading.py
shosai/parsing.py
shosai/base/__init__.py
shosai/base/resources.py
shosai/base/structure.py
shosai/commands/__init__.py
shosai/commands/shosai.py
shosai/commands/shosai_internal.py
shosai/docbase/__init__.py
shosai/docbase/configuration.py
shosai/docbase/resources.py
shosai/docbase/structure.py
shosai/docbase/transform.py
shosai-0.0.4.dist-info/METADATA
shosai-0.0.4.dist-info/WHEEL
shosai-0.0.4.dist-info/entry_points.txt
shosai-0.0.4.dist-info/top_level.txt
shosai-0.0.4.dist-info/RECORD
