Metadata-Version: 2.1
Name: shosai
Version: 0.0.4
Summary: -
Home-page: https://github.com/podhmo/shosai
Author: podhmo
Author-email: ababjam61+github@gmail.com
License: UNKNOWN
Keywords: markdown,docbase,hatena
Platform: UNKNOWN
Classifier: Programming Language :: Python
Classifier: Programming Language :: Python :: Implementation :: CPython
Requires-Dist: requests
Requires-Dist: requests-oauthlib
Requires-Dist: xmltodict
Requires-Dist: mistune
Requires-Dist: mypy-extensions
Provides-Extra: docs
Provides-Extra: testing
